[
  {
    "id": "1763105661479",
    "title_original": "隣の大学生との爛れた関係に溺れる欲求不満な未亡人 明里つむぎ",
    "url": "https://al.fanza.co.jp/?lurl=https%3A%2F%2Fvideo.dmm.co.jp%2Fav%2Fcontent%2F%3Fid%3Dadn00267&af_id=tecokey-003&ch=toolbar&ch_id=link",
    "title_final": "《明里つむぎ|未亡人》溜まりに溜まって欲求不満でオナニー三昧性活な美女が隣人の大学生と膣内射精セフレ関係になってしまう！",
    "thumb_original": "https://awsimgsrc.dmm.co.jp/pics_dig/digital/video/adn00267/adn00267pl.jpg?f=webp",
    "thumb_pick1": "https://awsimgsrc.dmm.co.jp/pics_dig/digital/video/adn00267/adn00267jp-10.jpg?f=webp",
    "thumb_pick2": "https://awsimgsrc.dmm.co.jp/pics_dig/digital/video/adn00267/adn00267jp-10.jpg?f=webp",
    "video": "https://video.laxd.com/ja/a/content/SQSRRSRYa7Sm46vi",
    "tags": [
      "未亡人",
      "ドラマ",
      "NTR",
      "寝取られ",
      "明里つむぎ",
      "オナニー",
      "中出し",
      "フェラ",
      "クンニ"
    ],
    "notes": "",
    "editor": "船長",
    "updated_at": "2025-11-16T11:21:03.914Z",
    "status": "edited"
  },
  {
    "id": "1763105725164",
    "title_original": "私が将来も人格も捨て引きこもりおさななじみの性処理を3年間し続けた理由 三葉ちはる",
    "url": "https://al.fanza.co.jp/?lurl=https%3A%2F%2Fvideo.dmm.co.jp%2Fav%2Fcontent%2F%3Fid%3D1fsdss00808&af_id=tecokey-003&ch=toolbar&ch_id=link",
    "title_final": "〈三葉ちはる|性処理〉人生捨てた幼馴染が放っとけなくてずっとち○この面倒を見てきたパイパン美少女！ま●こをタダ貸し⇒顔射",
    "thumb_original": "https://awsimgsrc.dmm.co.jp/pics_dig/digital/video/1fsdss00808/1fsdss00808pl.jpg?f=webp",
    "thumb_pick1": "https://awsimgsrc.dmm.co.jp/pics_dig/digital/video/1fsdss00808/1fsdss00808jp-10.jpg?f=webp",
    "thumb_pick2": "https://awsimgsrc.dmm.co.jp/pics_dig/digital/video/1fsdss00808/1fsdss00808jp-6.jpg?f=webp",
    "video": "https://vjav.com/videos/859073/x3xc535be22b3d819cdc5/",
    "tags": [
      "幼なじみ",
      "女子大生",
      "騎乗位",
      "パイパン",
      "顔射",
      "ぶっかけ",
      "フェラ",
      "クンニ",
      "ドラマ",
      "単体作品",
      "美少女"
    ],
    "notes": "",
    "editor": "船長",
    "updated_at": "2025-11-16T11:47:37.238Z",
    "status": "edited"
  },
  {
    "id": "1763105761492",
    "title_original": "禁欲の果て、汗と絶頂汁まみれで交わりまくった3日間 桜空もも",
    "url": "https://al.fanza.co.jp/?lurl=https%3A%2F%2Fvideo.dmm.co.jp%2Fav%2Fcontent%2F%3Fid%3Dipx00743&af_id=tecokey-003&ch=toolbar&ch_id=link",
    "title_final": "〖桜空もも|汗だく騎乗位〗ゴムありだからこそのエロ演出っ♡スケスケニーハイ上下ピストン連続SEXで搾精飲精⇒精液貯蓄ッ♡",
    "thumb_original": "https://awsimgsrc.dmm.co.jp/pics_dig/digital/video/ipx00743/ipx00743pl.jpg?f=webp",
    "thumb_pick1": "https://awsimgsrc.dmm.co.jp/pics_dig/digital/video/ipx00743/ipx00743jp-12.jpg?f=webp",
    "thumb_pick2": "https://awsimgsrc.dmm.co.jp/pics_dig/digital/video/ipx00743/ipx00743jp-7.jpg?f=webp",
    "video": "https://video.laxd.com/ja/a/content/SQSTQWQRhcslUSRR",
    "tags": [
      "汗だく",
      "フェラ",
      "巨乳",
      "桜空もも",
      "騎乗位",
      "ごっくん",
      "手コキ",
      "単体作品"
    ],
    "notes": "",
    "editor": "船長",
    "updated_at": "2025-11-16T12:09:21.196Z",
    "status": "edited"
  },
  {
    "id": "1763229382285",
    "title_original": "身も心も相性抜群の2人ー。’想い’と’唇’が重なる濃密接吻ソープ 篠原いよ",
    "url": "https://al.fanza.co.jp/?lurl=https%3A%2F%2Fvideo.dmm.co.jp%2Fav%2Fcontent%2F%3Fid%3Djur00488&af_id=tecokey-003&ch=toolbar&ch_id=link",
    "title_final": "〖篠原いよ★最強人妻ソープ〗無敵の女優が風俗でマットプレイっ♡濃厚おもてなし手コキで暴発⇒生挿入膣内射精でリピート確定♡",
    "thumb_original": "https://awsimgsrc.dmm.co.jp/pics_dig/digital/video/jur00488/jur00488pl.jpg?f=webp",
    "thumb_pick1": "https://awsimgsrc.dmm.co.jp/pics_dig/digital/video/jur00488/jur00488jp-10.jpg?f=webp",
    "thumb_pick2": "https://awsimgsrc.dmm.co.jp/pics_dig/digital/video/jur00488/jur00488jp-4.jpg?f=webp",
    "video": "https://txxx.com/videos/21189121/x1x68b925155e08697ec6/?promo=38693",
    "tags": [
      "篠原いよ",
      "熟女",
      "中出し",
      "人妻",
      "爆乳",
      "パイパン",
      "手コキ",
      "騎乗位",
      "単体作品"
    ],
    "notes": "",
    "editor": "船長",
    "updated_at": "2025-11-16T12:15:22.152Z",
    "status": "edited"
  },
  {
    "id": "1763105693246",
    "title_original": "町内キャンプNTR テントの中で何度も中出しされた妻の【閲覧注意】寝取られ映像 神宮寺ナオ",
    "url": "https://al.fanza.co.jp/?lurl=https%3A%2F%2Fvideo.dmm.co.jp%2Fav%2Fcontent%2F%3Fid%3Djul00568&af_id=tecokey-003&ch=toolbar&ch_id=link",
    "title_final": "〖神宮寺ナオ★NTRキャンプ〗テント内で複数人に寝取られる巨乳人妻っ♡エロい身体は敏感に反応して串刺し膣内射精翌日も…ッ",
    "thumb_original": "https://awsimgsrc.dmm.co.jp/pics_dig/digital/video/jul00568/jul00568pl.jpg?f=webp",
    "thumb_pick1": "https://awsimgsrc.dmm.co.jp/pics_dig/digital/video/jul00568/jul00568jp-5.jpg?f=webp",
    "thumb_pick2": "https://awsimgsrc.dmm.co.jp/pics_dig/digital/video/jul00568/jul00568jp-4.jpg?f=webp",
    "video": "https://video.laxd.com/ja/a/content/SQSUQXQYO2PIMVZg",
    "tags": [
      "神宮寺ナオ",
      "巨乳",
      "中出し",
      "人妻",
      "熟女",
      "NTR",
      "寝取られ",
      "輪姦",
      "複数プレイ",
      "単体作品",
      "フェラ"
    ],
    "notes": "",
    "editor": "船長",
    "updated_at": "2025-11-16T12:17:11.925Z",
    "status": "edited"
  },
  {
    "id": "1763229875244",
    "title_original": "どっちに中出ししたいXmas AV女優2人がガチで考えたデートプランでいちゃいちゃ恋人SEX 二股浮気がバレてお仕置き精子抜き中出しハーレムクリスマスSpecial 森日向子 弥生みづき",
    "url": "https://al.fanza.co.jp/?lurl=https%3A%2F%2Fvideo.dmm.co.jp%2Fav%2Fcontent%2F%3Fid%3Dhmn00400&af_id=tecokey-003&ch=toolbar&ch_id=link",
    "title_final": "〖弥生みづき×森日向子〗冬のサンタがおまんこの温もりをプレゼントっ♡どっちに膣内射精してもOK！連続膣射クリスマスッ♡…",
    "thumb_original": "https://awsimgsrc.dmm.co.jp/pics_dig/digital/video/hmn00400/hmn00400pl.jpg?f=webp",
    "thumb_pick1": "https://awsimgsrc.dmm.co.jp/pics_dig/digital/video/hmn00400/hmn00400jp-4.jpg?f=webp",
    "thumb_pick2": "https://awsimgsrc.dmm.co.jp/pics_dig/digital/video/hmn00400/hmn00400pl.jpg?f=webp",
    "video": "https://upornia.com/videos/6017011/mbabvzkcyzkwfsobvw36hmn400/?promo=47941",
    "tags": [
      "弥生みづき",
      "森日向子",
      "巨乳",
      "パイパン",
      "中出し",
      "フェラ",
      "騎乗位",
      "手マン",
      "クンニ"
    ],
    "notes": "",
    "editor": "船長",
    "updated_at": "2025-11-16T12:28:59.267Z",
    "status": "edited"
  },
  {
    "id": "1763229957223",
    "title_original": "羞恥！彼氏連れ素人娘をマシンバイブでこっそり攻めまくれ！24 素人VSマシンバイブ 激安居酒屋にマジックミラー特設スタジオを設置 ハッピーメリーマシンバイブ！クリも子宮もまとめて絶頂させる激ピス波動エグち！",
    "url": "https://al.fanza.co.jp/?lurl=https%3A%2F%2Fvideo.dmm.co.jp%2Fav%2Fcontent%2F%3Fid%3D1svdvd00947&af_id=tecokey-003&ch=toolbar&ch_id=link",
    "title_final": "〈素人GAL★マシンバイブ〉『メリークリトリスっ♪』激ピス玩具で盛大に潮吹きっ♡絶頂ま●こに本物精液膣内射精プレゼント♡",
    "thumb_original": "https://awsimgsrc.dmm.co.jp/pics_dig/digital/video/1svdvd00947/1svdvd00947pl.jpg?f=webp",
    "thumb_pick1": "https://awsimgsrc.dmm.co.jp/pics_dig/digital/video/1svdvd00947/1svdvd00947jp-3.jpg?f=webp",
    "thumb_pick2": "https://awsimgsrc.dmm.co.jp/pics_dig/digital/video/1svdvd00947/1svdvd00947jp-2.jpg?f=webp",
    "video": "https://senzuri.tube/videos/10262769/tqmn14-cuteeeee-asian-sex-oh-yeah/?promo=47072",
    "tags": [
      "素人",
      "おもちゃ",
      "潮吹き",
      "中出し",
      "巨乳",
      "乱交",
      "複数プレイ",
      "電マ",
      "顔射"
    ],
    "notes": "",
    "editor": "船長",
    "updated_at": "2025-11-16T13:18:39.255Z",
    "status": "edited"
  },
  {
    "id": "1763229477606",
    "title_original": "妻には口が裂けても言えません、義母さんを孕ませてしまったなんて…。-1泊2日の温泉旅行で、我を忘れて中出ししまくった僕。- 篠原いよ",
    "url": "https://al.fanza.co.jp/?lurl=https%3A%2F%2Fvideo.dmm.co.jp%2Fav%2Fcontent%2F%3Fid%3Djur00356&af_id=tecokey-003&ch=toolbar&ch_id=link",
    "title_final": "《篠原いよ×温泉旅行》妻に内緒で爆乳Hcup義母と膣内射精SEX…顔も神乳おっぱいも無毛まんこも美しすぎて無意識誘惑っ♡",
    "thumb_original": "https://awsimgsrc.dmm.co.jp/pics_dig/digital/video/jur00356/jur00356pl.jpg?f=webp",
    "thumb_pick1": "https://awsimgsrc.dmm.co.jp/pics_dig/digital/video/jur00356/jur00356jp-1.jpg?f=webp",
    "thumb_pick2": "https://awsimgsrc.dmm.co.jp/pics_dig/digital/video/jur00356/jur00356jp-3.jpg?f=webp",
    "video": "https://upornia.com/videos/6200819/a/?promo=47941",
    "tags": [
      "篠原いよ",
      "中出し",
      "巨乳",
      "熟女",
      "人妻",
      "温泉",
      "パイパン",
      "フェラ",
      "手コキ",
      "手マン",
      "単体作品"
    ],
    "notes": "",
    "editor": "船長",
    "updated_at": "2025-11-16T13:26:25.862Z",
    "status": "edited"
  },
  {
    "id": "1763232058472",
    "title_original": "【神スタイル×長身美脚×中出し4連発】ざわ…ざわ… 圧倒的美脚っ…！ざわ… 悪魔的スタイルっ…！！爆速騎乗位で中出し、顔射4連発！このギャル正に沼っ…！精液を飲み込むドエロ沼っ…！このギャルに出会えた事、圧倒的感謝っ…！！次回予告「エロは命より重い！最強のエロギャル登場！！」【ギャルしべ長者35人目 さりな】",
    "url": "https://www.mgstage.com/product/product_detail/390JAC-060/?form=mgs_asp_linktool_CD3AKPJX3YNY8KY5GSFJ47S24J&utm_medium=mgs_affiliate&utm_source=mgs_affiliate_linktool&utm_campaign=mgs_affiliate_linktool&utm_content=CD3AKPJX3YNY8KY5GSFJ47S24J&agef=1&aff=CD3AKPJX3YNY8KY5GSFJ47S24J",
    "title_final": "《金髪GAL★巨乳美脚》長身神スタイルの美女のま●こは超敏感っ♡電マでガクガクになっても騎乗位でチ○ポを搾るっっ♡♡♡",
    "thumb_original": "https://image.mgstage.com/images/jackson/390jac/060/pb_e_390jac-060.jpg",
    "thumb_pick1": "https://image.mgstage.com/images/jackson/390jac/060/cap_e_10_390jac-060.jpg",
    "thumb_pick2": "https://image.mgstage.com/images/jackson/390jac/060/cap_e_18_390jac-060.jpg",
    "video": "https://do-ga.eroterest.net/video/detail/3355/",
    "tags": [
      "巨乳",
      "ギャル",
      "長身",
      "素人",
      "美脚",
      "電マ",
      "オナニー",
      "騎乗位",
      "おもちゃ"
    ],
    "notes": "",
    "editor": "船長",
    "updated_at": "2025-11-16T13:33:56.818Z",
    "status": "edited"
  }
]