[
  {
    "id": "1773223306654",
    "title_original": "ナチュラルハイ年末スペシャル 痴●OK娘 全裸露出編 絶対NGの美肌巨乳美少女を野外羞恥の快感で中出しまでOKさせろ",
    "url": "https://al.fanza.co.jp/?lurl=https%3A%2F%2Fvideo.dmm.co.jp%2Fav%2Fcontent%2F%3Fid%3D1nhdtb00852&af_id=tecokey-003&ch=toolbar&ch_id=link",
    "title_final": "〚痴漢★美巨乳JK〛公認露出で電車内で触られ潮吹きッ♡ビクンビクンイキすぎてお礼に手コキで尻射フィニッシュっっ♡♡♡",
    "thumb_original": "https://awsimgsrc.dmm.co.jp/pics_dig/digital/video/1nhdtb00852/1nhdtb00852pl.jpg?f=webp",
    "thumb_pick1": "https://awsimgsrc.dmm.co.jp/pics_dig/digital/video/1nhdtb00852/1nhdtb00852jp-5.jpg?f=webp",
    "thumb_pick2": "https://awsimgsrc.dmm.co.jp/pics_dig/digital/video/1nhdtb00852/1nhdtb00852jp-6.jpg?f=webp",
    "video": "https://txxx.com/videos/19894623/x1xa259dc65d327c88ac3/?promo=48097",
    "tags": [
      "巨乳",
      "女子校生",
      "痴漢",
      "潮吹き",
      "手コキ",
      "手マン",
      "ぶっかけ",
      "露出"
    ],
    "notes": "",
    "editor": "神",
    "updated_at": "2026-04-24T03:26:42.012Z",
    "status": "edited"
  },
  {
    "id": "1770436894347",
    "title_original": "【マジ惚れ逆NTR】Fカップ最強中卒ギャルが逆ナンパ！！禁断の寝取りドキュメント！！筋肉フェチの巨乳スレンダーGALがマッチョを逆ナンしたら凄い事になった件！！！大好きモード突入でカノジョから奪う気満々！！淫語満載ガチ騎乗位SEXで本気の本気で寝取る！！！ぎゅうぎゅう締め付け生マ◯コで中出し希望！！！【NTRリバース】",
    "url": "https://www.mgstage.com/product/product_detail/300MIUM-910/?form=mgs_asp_linktool_CD3AKPJX3YNY8KY5GSFJ47S24J&utm_medium=mgs_affiliate&utm_source=mgs_affiliate_linktool&utm_campaign=mgs_affiliate_linktool&utm_content=CD3AKPJX3YNY8KY5GSFJ47S24J&agef=1&aff=CD3AKPJX3YNY8KY5GSFJ47S24J",
    "title_final": "《Fカップ最強中卒GAL×逆NTR》逆ナンしたマッチョにガチ惚れ⇒美巨乳スレンダーま●こが疼いてザーメン欲しがり顔射ッ♡",
    "thumb_original": "https://image.mgstage.com/images/prestigepremium/300mium/910/pb_e_300mium-910.jpg",
    "thumb_pick1": "https://image.mgstage.com/images/prestigepremium/300mium/910/cap_e_34_300mium-910.jpg",
    "thumb_pick2": "https://image.mgstage.com/images/prestigepremium/300mium/910/cap_e_34_300mium-910.jpg",
    "video": "https://do-ga.eroterest.net/video/detail/17453/?promo=48097",
    "tags": [
      "素人",
      "企画",
      "ギャル",
      "痴女",
      "巨乳",
      "オナニー",
      "フェラ",
      "顔射",
      "おもちゃ",
      "NTR",
      "寝取られ"
    ],
    "notes": "",
    "editor": "神",
    "updated_at": "2026-04-24T03:35:51.850Z",
    "status": "edited"
  }
]